odoo/addons/budget_plan_detail_purchase/README.rst
odoo/addons/budget_plan_detail_purchase/__init__.py
odoo/addons/budget_plan_detail_purchase/__manifest__.py
odoo/addons/budget_plan_detail_purchase/hooks.py
odoo/addons/budget_plan_detail_purchase/models/__init__.py
odoo/addons/budget_plan_detail_purchase/models/account_analytic_dimension.py
odoo/addons/budget_plan_detail_purchase/models/purchase.py
odoo/addons/budget_plan_detail_purchase/readme/CONTRIBUTORS.md
odoo/addons/budget_plan_detail_purchase/readme/DESCRIPTION.md
odoo/addons/budget_plan_detail_purchase/report/__init__.py
odoo/addons/budget_plan_detail_purchase/report/budget_source_fund_report.py
odoo/addons/budget_plan_detail_purchase/static/description/icon.png
odoo/addons/budget_plan_detail_purchase/static/description/index.html
odoo/addons/budget_plan_detail_purchase/tests/__init__.py
odoo/addons/budget_plan_detail_purchase/tests/test_budget_plan_detail_purchase.py
odoo/addons/budget_plan_detail_purchase/views/purchase_budget_move.xml
odoo/addons/budget_plan_detail_purchase/views/purchase_view.xml
odoo_addon_budget_plan_detail_purchase-18.0.1.1.3.dist-info/METADATA
odoo_addon_budget_plan_detail_purchase-18.0.1.1.3.dist-info/WHEEL
odoo_addon_budget_plan_detail_purchase-18.0.1.1.3.dist-info/top_level.txt
odoo_addon_budget_plan_detail_purchase-18.0.1.1.3.dist-info/RECORD
